[
    {
      "waveid": 1,
      "enemy_01_1": 3,
      "enemy_01_2": 0,
      "enemy_01_3": 0,
      "enemy_01_4": 0,
      "boss_01": 0,
      "boss_02": 0,
      "boss_03": 0,
      "boss_04": 0
    },
    {
      "waveid": 2,
      "enemy_01_1": 5,
      "enemy_01_2": 0,
      "enemy_01_3": 0,
      "enemy_01_4": 0,
      "boss_01": 0,
      "boss_02": 0,
      "boss_03": 0,
      "boss_04": 0
    },
    {
      "waveid": 3,
      "enemy_01_1": 8,
      "enemy_01_2": 0,
      "enemy_01_3": 0,
      "enemy_01_4": 0,
      "boss_01": 0,
      "boss_02": 0,
      "boss_03": 0,
      "boss_04": 0
    },
    {
      "waveid": 4,
      "enemy_01_1": 12,
      "enemy_01_2": 0,
      "enemy_01_3": 0,
      "enemy_01_4": 0,
      "boss_01": 0,
      "boss_02": 0,
      "boss_03": 0,
      "boss_04": 0
    },
    {
      "waveid": 5,
      "enemy_01_1": 16,
      "enemy_01_2": 0,
      "enemy_01_3": 0,
      "enemy_01_4": 0,
      "boss_01": 0,
      "boss_02": 0,
      "boss_03": 0,
      "boss_04": 0
    },
    {
      "waveid": 6,
      "enemy_01_1": 20,
      "enemy_01_2": 0,
      "enemy_01_3": 0,
      "enemy_01_4": 0,
      "boss_01": 0,
      "boss_02": 0,
      "boss_03": 0,
      "boss_04": 0
    },
    {
      "waveid": 7,
      "enemy_01_1": 24,
      "enemy_01_2": 0,
      "enemy_01_3": 0,
      "enemy_01_4": 0,
      "boss_01": 0,
      "boss_02": 0,
      "boss_03": 0,
      "boss_04": 0
    },
    {
      "waveid": 8,
      "enemy_01_1": 28,
      "enemy_01_2": 0,
      "enemy_01_3": 0,
      "enemy_01_4": 0,
      "boss_01": 0,
      "boss_02": 0,
      "boss_03": 0,
      "boss_04": 0
    },
    {
      "waveid": 9,
      "enemy_01_1": 32,
      "enemy_01_2": 0,
      "enemy_01_3": 0,
      "enemy_01_4": 0,
      "boss_01": 0,
      "boss_02": 0,
      "boss_03": 0,
      "boss_04": 0
    },
    {
      "waveid": 10,
      "enemy_01_1": 0,
      "enemy_01_2": 0,
      "enemy_01_3": 0,
      "enemy_01_4": 0,
      "boss_01": 1,
      "boss_02": 0,
      "boss_03": 0,
      "boss_04": 0
    },
    {
      "waveid": 11,
      "enemy_01_1": 40,
      "enemy_01_2": 3,
      "enemy_01_3": 0,
      "enemy_01_4": 0,
      "boss_01": 0,
      "boss_02": 0,
      "boss_03": 0,
      "boss_04": 0
    },
    {
      "waveid": 12,
      "enemy_01_1": 40,
      "enemy_01_2": 5,
      "enemy_01_3": 0,
      "enemy_01_4": 0,
      "boss_01": 0,
      "boss_02": 0,
      "boss_03": 0,
      "boss_04": 0
    },
    {
      "waveid": 13,
      "enemy_01_1": 40,
      "enemy_01_2": 8,
      "enemy_01_3": 0,
      "enemy_01_4": 0,
      "boss_01": 0,
      "boss_02": 0,
      "boss_03": 0,
      "boss_04": 0
    },
    {
      "waveid": 14,
      "enemy_01_1": 40,
      "enemy_01_2": 12,
      "enemy_01_3": 0,
      "enemy_01_4": 0,
      "boss_01": 0,
      "boss_02": 0,
      "boss_03": 0,
      "boss_04": 0
    },
    {
      "waveid": 15,
      "enemy_01_1": 40,
      "enemy_01_2": 16,
      "enemy_01_3": 0,
      "enemy_01_4": 0,
      "boss_01": 0,
      "boss_02": 0,
      "boss_03": 0,
      "boss_04": 0
    },
    {
      "waveid": 16,
      "enemy_01_1": 40,
      "enemy_01_2": 20,
      "enemy_01_3": 0,
      "enemy_01_4": 0,
      "boss_01": 0,
      "boss_02": 0,
      "boss_03": 0,
      "boss_04": 0
    },
    {
      "waveid": 17,
      "enemy_01_1": 40,
      "enemy_01_2": 24,
      "enemy_01_3": 0,
      "enemy_01_4": 0,
      "boss_01": 0,
      "boss_02": 0,
      "boss_03": 0,
      "boss_04": 0
    },
    {
      "waveid": 18,
      "enemy_01_1": 40,
      "enemy_01_2": 28,
      "enemy_01_3": 0,
      "enemy_01_4": 0,
      "boss_01": 0,
      "boss_02": 0,
      "boss_03": 0,
      "boss_04": 0
    },
    {
      "waveid": 19,
      "enemy_01_1": 40,
      "enemy_01_2": 32,
      "enemy_01_3": 0,
      "enemy_01_4": 0,
      "boss_01": 0,
      "boss_02": 0,
      "boss_03": 0,
      "boss_04": 0
    },
    {
      "waveid": 20,
      "enemy_01_1": 40,
      "enemy_01_2": 40,
      "enemy_01_3": 0,
      "enemy_01_4": 0,
      "boss_01": 0,
      "boss_02": 1,
      "boss_03": 0,
      "boss_04": 0
    },
    {
      "waveid": 21,
      "enemy_01_1": 0,
      "enemy_01_2": 40,
      "enemy_01_3": 3,
      "enemy_01_4": 0,
      "boss_01": 0,
      "boss_02": 0,
      "boss_03": 0,
      "boss_04": 0
    },
    {
      "waveid": 22,
      "enemy_01_1": 0,
      "enemy_01_2": 40,
      "enemy_01_3": 5,
      "enemy_01_4": 0,
      "boss_01": 0,
      "boss_02": 0,
      "boss_03": 0,
      "boss_04": 0
    },
    {
      "waveid": 23,
      "enemy_01_1": 0,
      "enemy_01_2": 40,
      "enemy_01_3": 8,
      "enemy_01_4": 0,
      "boss_01": 0,
      "boss_02": 0,
      "boss_03": 0,
      "boss_04": 0
    },
    {
      "waveid": 24,
      "enemy_01_1": 0,
      "enemy_01_2": 40,
      "enemy_01_3": 12,
      "enemy_01_4": 0,
      "boss_01": 0,
      "boss_02": 0,
      "boss_03": 0,
      "boss_04": 0
    },
    {
      "waveid": 25,
      "enemy_01_1": 0,
      "enemy_01_2": 40,
      "enemy_01_3": 16,
      "enemy_01_4": 0,
      "boss_01": 0,
      "boss_02": 0,
      "boss_03": 0,
      "boss_04": 0
    },
    {
      "waveid": 26,
      "enemy_01_1": 0,
      "enemy_01_2": 40,
      "enemy_01_3": 20,
      "enemy_01_4": 0,
      "boss_01": 0,
      "boss_02": 0,
      "boss_03": 0,
      "boss_04": 0
    },
    {
      "waveid": 27,
      "enemy_01_1": 0,
      "enemy_01_2": 40,
      "enemy_01_3": 24,
      "enemy_01_4": 0,
      "boss_01": 0,
      "boss_02": 0,
      "boss_03": 0,
      "boss_04": 0
    },
    {
      "waveid": 28,
      "enemy_01_1": 0,
      "enemy_01_2": 40,
      "enemy_01_3": 28,
      "enemy_01_4": 0,
      "boss_01": 0,
      "boss_02": 0,
      "boss_03": 0,
      "boss_04": 0
    },
    {
      "waveid": 29,
      "enemy_01_1": 0,
      "enemy_01_2": 40,
      "enemy_01_3": 32,
      "enemy_01_4": 0,
      "boss_01": 0,
      "boss_02": 0,
      "boss_03": 0,
      "boss_04": 0
    },
    {
      "waveid": 30,
      "enemy_01_1": 0,
      "enemy_01_2": 40,
      "enemy_01_3": 40,
      "enemy_01_4": 0,
      "boss_01": 0,
      "boss_02": 0,
      "boss_03": 1,
      "boss_04": 0
    },
    {
      "waveid": 31,
      "enemy_01_1": 0,
      "enemy_01_2": 0,
      "enemy_01_3": 40,
      "enemy_01_4": 3,
      "boss_01": 0,
      "boss_02": 0,
      "boss_03": 0,
      "boss_04": 0
    },
    {
      "waveid": 32,
      "enemy_01_1": 0,
      "enemy_01_2": 0,
      "enemy_01_3": 40,
      "enemy_01_4": 5,
      "boss_01": 0,
      "boss_02": 0,
      "boss_03": 0,
      "boss_04": 0
    },
    {
      "waveid": 33,
      "enemy_01_1": 0,
      "enemy_01_2": 0,
      "enemy_01_3": 40,
      "enemy_01_4": 8,
      "boss_01": 0,
      "boss_02": 0,
      "boss_03": 0,
      "boss_04": 0
    },
    {
      "waveid": 34,
      "enemy_01_1": 0,
      "enemy_01_2": 0,
      "enemy_01_3": 40,
      "enemy_01_4": 12,
      "boss_01": 0,
      "boss_02": 0,
      "boss_03": 0,
      "boss_04": 0
    },
    {
      "waveid": 35,
      "enemy_01_1": 0,
      "enemy_01_2": 0,
      "enemy_01_3": 40,
      "enemy_01_4": 16,
      "boss_01": 0,
      "boss_02": 0,
      "boss_03": 0,
      "boss_04": 0
    },
    {
      "waveid": 36,
      "enemy_01_1": 0,
      "enemy_01_2": 0,
      "enemy_01_3": 40,
      "enemy_01_4": 20,
      "boss_01": 0,
      "boss_02": 0,
      "boss_03": 0,
      "boss_04": 0
    },
    {
      "waveid": 37,
      "enemy_01_1": 0,
      "enemy_01_2": 0,
      "enemy_01_3": 40,
      "enemy_01_4": 24,
      "boss_01": 0,
      "boss_02": 0,
      "boss_03": 0,
      "boss_04": 0
    },
    {
      "waveid": 38,
      "enemy_01_1": 0,
      "enemy_01_2": 0,
      "enemy_01_3": 40,
      "enemy_01_4": 28,
      "boss_01": 0,
      "boss_02": 0,
      "boss_03": 0,
      "boss_04": 0
    },
    {
      "waveid": 39,
      "enemy_01_1": 0,
      "enemy_01_2": 0,
      "enemy_01_3": 40,
      "enemy_01_4": 30,
      "boss_01": 0,
      "boss_02": 0,
      "boss_03": 0,
      "boss_04": 0
    },
    {
      "waveid": 40,
      "enemy_01_1": 0,
      "enemy_01_2": 0,
      "enemy_01_3": 40,
      "enemy_01_4": 32,
      "boss_01": 0,
      "boss_02": 0,
      "boss_03": 0,
      "boss_04": 1
    }
  ]